censuswrangler/__init__.py
censuswrangler/_data.py
censuswrangler/_pack.py
censuswrangler/_schemas.py
censuswrangler/census.py
censuswrangler/config.py
censuswrangler/config_template.csv
censuswrangler-1.0.5.dist-info/licenses/LICENSE
censuswrangler-1.0.5.dist-info/METADATA
censuswrangler-1.0.5.dist-info/WHEEL
censuswrangler-1.0.5.dist-info/RECORD
