Metadata-Version: 2.4
Name: censuswrangler
Version: 1.0.5
Summary: CensusWrangler is the fast python API to your local copy of the Australian Census data.
License: MIT
License-File: LICENSE
Author: Kyle Ross
Author-email: 107285758+Kyle-Ross@users.noreply.github.com
Requires-Python: >=3.12,<4.0
Classifier: License :: OSI Approved :: MIT License
Classifier: Programming Language :: Python :: 3
Classifier: Programming Language :: Python :: 3.12
Classifier: Programming Language :: Python :: 3.13
Classifier: Programming Language :: Python :: 3.14
Requires-Dist: icecream (>=2.1.4,<3.0.0)
Requires-Dist: openpyxl (>=3.1.5,<4.0.0)
Requires-Dist: pandas (>=2.2.3,<3.0.0)
Requires-Dist: pandera (>=0.23.1,<0.24.0)
